binja_test_mocks/__init__.py
binja_test_mocks/binja_api.py
binja_test_mocks/coding.py
binja_test_mocks/eval_llil.py
binja_test_mocks/mock_analysis.py
binja_test_mocks/mock_binaryview.py
binja_test_mocks/mock_llil.py
binja_test_mocks/py.typed
binja_test_mocks/tokens.py
binja_test_mocks/scripts/__init__.py
binja_test_mocks/scripts/run_tests.py
binja_test_mocks/stubs/binaryninja/__init__.pyi
binja_test_mocks/stubs/binaryninja/architecture.pyi
binja_test_mocks/stubs/binaryninja/binaryview.pyi
binja_test_mocks/stubs/binaryninja/enums.pyi
binja_test_mocks/stubs/binaryninja/function.pyi
binja_test_mocks/stubs/binaryninja/interaction.pyi
binja_test_mocks/stubs/binaryninja/log.pyi
binja_test_mocks/stubs/binaryninja/lowlevelil.pyi
binja_test_mocks/stubs/binaryninja/plugin.pyi
binja_test_mocks/stubs/binaryninja/types.pyi
binja_test_mocks-0.1.10.dist-info/METADATA
binja_test_mocks-0.1.10.dist-info/WHEEL
binja_test_mocks-0.1.10.dist-info/entry_points.txt
binja_test_mocks-0.1.10.dist-info/licenses/LICENSE
binja_test_mocks-0.1.10.dist-info/RECORD
