Metadata-Version: 2.4
Name: binja-test-mocks
Version: 0.1.10
Summary: Mock Binary Ninja API for testing Binary Ninja plugins without requiring a license
Project-URL: Homepage, https://github.com/mblsha/binja-test-mocks
Project-URL: Repository, https://github.com/mblsha/binja-test-mocks
Project-URL: Issues, https://github.com/mblsha/binja-test-mocks/issues
Author: mblsha
License: MIT
License-File: LICENSE
Keywords: binary ninja,mocks,reverse engineering,testing
Classifier: Development Status :: 4 - Beta
Classifier: Intended Audience :: Developers
Classifier: License :: OSI Approved :: MIT License
Classifier: Programming Language :: Python :: 3
Classifier: Programming Language :: Python :: 3.10
Classifier: Programming Language :: Python :: 3.11
Classifier: Programming Language :: Python :: 3.12
Classifier: Topic :: Software Development :: Testing
Classifier: Topic :: Software Development :: Testing :: Mocking
Requires-Python: >=3.10
Provides-Extra: dev
Requires-Dist: build>=0.10; extra == 'dev'
Requires-Dist: mypy>=1.0; extra == 'dev'
Requires-Dist: pyright>=1.1; extra == 'dev'
Requires-Dist: pytest-cov>=4.0; extra == 'dev'
Requires-Dist: pytest>=7.0; extra == 'dev'
Requires-Dist: ruff>=0.1; extra == 'dev'
Requires-Dist: twine>=4.0; extra == 'dev'
